LICENSE
README.md
setup.py
NlpToolkit_SemanticRoleLabeling_Cy.egg-info/PKG-INFO
NlpToolkit_SemanticRoleLabeling_Cy.egg-info/SOURCES.txt
NlpToolkit_SemanticRoleLabeling_Cy.egg-info/dependency_links.txt
NlpToolkit_SemanticRoleLabeling_Cy.egg-info/requires.txt
NlpToolkit_SemanticRoleLabeling_Cy.egg-info/top_level.txt
SemanticRoleLabeling/__init__.py
SemanticRoleLabeling/AutoProcessor/__init__.py
SemanticRoleLabeling/AutoProcessor/ParseTree/__init__.py
SemanticRoleLabeling/AutoProcessor/ParseTree/Propbank/AutoArgument.c
SemanticRoleLabeling/AutoProcessor/ParseTree/Propbank/AutoArgument.pyx
SemanticRoleLabeling/AutoProcessor/ParseTree/Propbank/__init__.py
SemanticRoleLabeling/AutoProcessor/Sentence/__init__.py
SemanticRoleLabeling/AutoProcessor/Sentence/FrameNet/SentenceAutoFramePredicate.c
SemanticRoleLabeling/AutoProcessor/Sentence/FrameNet/SentenceAutoFramePredicate.pxd
SemanticRoleLabeling/AutoProcessor/Sentence/FrameNet/SentenceAutoFramePredicate.pyx
SemanticRoleLabeling/AutoProcessor/Sentence/FrameNet/TurkishSentenceAutoFramePredicate.c
SemanticRoleLabeling/AutoProcessor/Sentence/FrameNet/TurkishSentenceAutoFramePredicate.pyx
SemanticRoleLabeling/AutoProcessor/Sentence/FrameNet/__init__.py
SemanticRoleLabeling/AutoProcessor/Sentence/Propbank/SentenceAutoArgument.c
SemanticRoleLabeling/AutoProcessor/Sentence/Propbank/SentenceAutoArgument.pxd
SemanticRoleLabeling/AutoProcessor/Sentence/Propbank/SentenceAutoArgument.pyx
SemanticRoleLabeling/AutoProcessor/Sentence/Propbank/SentenceAutoPredicate.c
SemanticRoleLabeling/AutoProcessor/Sentence/Propbank/SentenceAutoPredicate.pxd
SemanticRoleLabeling/AutoProcessor/Sentence/Propbank/SentenceAutoPredicate.pyx
SemanticRoleLabeling/AutoProcessor/Sentence/Propbank/TurkishSentenceAutoArgument.c
SemanticRoleLabeling/AutoProcessor/Sentence/Propbank/TurkishSentenceAutoArgument.pyx
SemanticRoleLabeling/AutoProcessor/Sentence/Propbank/TurkishSentenceAutoPredicate.c
SemanticRoleLabeling/AutoProcessor/Sentence/Propbank/TurkishSentenceAutoPredicate.pyx
SemanticRoleLabeling/AutoProcessor/Sentence/Propbank/__init__.py
nlptoolkit_semanticrolelabeling_cy.egg-info/PKG-INFO
nlptoolkit_semanticrolelabeling_cy.egg-info/SOURCES.txt
nlptoolkit_semanticrolelabeling_cy.egg-info/dependency_links.txt
nlptoolkit_semanticrolelabeling_cy.egg-info/requires.txt
nlptoolkit_semanticrolelabeling_cy.egg-info/top_level.txt