Metadata-Version: 2.4
Name: nlptoolkit-semanticrolelabeling-cy
Version: 1.0.7
Summary: Semantic Role Labeling Library
Home-page: https://github.com/StarlangSoftware/SemanticRoleLabeling-Cy
Author: olcaytaner
Author-email: olcay.yildiz@ozyegin.edu.tr
License-File: LICENSE
Requires-Dist: NlpToolkit-AnnotatedTree-Cy
Dynamic: author
Dynamic: author-email
Dynamic: description
Dynamic: description-content-type
Dynamic: home-page
Dynamic: license-file
Dynamic: requires-dist
Dynamic: summary
